BaseSDK/BASEClient.py
BaseSDK/ClientException.py
BaseSDK/Configuration.py
BaseSDK/Utils.py
BaseSDK/__init__.py
BaseSDK-0.2.23.dist-info/LICENSE.txt
BaseSDK-0.2.23.dist-info/METADATA
BaseSDK-0.2.23.dist-info/WHEEL
BaseSDK-0.2.23.dist-info/top_level.txt
BaseSDK-0.2.23.dist-info/RECORD
