Metadata-Version: 2.1
Name: BaseSDK
Version: 0.2.23
Summary: UNKNOWN
Home-page: https://github.com/boden-ai/base-sdk.git
Author: joey
Author-email: yi.zhao@bodenai.com
License: UNKNOWN
Platform: UNKNOWN
License-File: LICENSE.txt
Requires-Dist: requests
